odoo9_addon_fetchmail_notify_error_to_sender-9.0.1.0.0-py2.7-nspkg.pth
odoo9_addon_fetchmail_notify_error_to_sender-9.0.1.0.0.dist-info/DESCRIPTION.rst
odoo9_addon_fetchmail_notify_error_to_sender-9.0.1.0.0.dist-info/METADATA
odoo9_addon_fetchmail_notify_error_to_sender-9.0.1.0.0.dist-info/RECORD
odoo9_addon_fetchmail_notify_error_to_sender-9.0.1.0.0.dist-info/WHEEL
odoo9_addon_fetchmail_notify_error_to_sender-9.0.1.0.0.dist-info/metadata.json
odoo9_addon_fetchmail_notify_error_to_sender-9.0.1.0.0.dist-info/namespace_packages.txt
odoo9_addon_fetchmail_notify_error_to_sender-9.0.1.0.0.dist-info/top_level.txt
odoo_addons/fetchmail_notify_error_to_sender/README.rst
odoo_addons/fetchmail_notify_error_to_sender/__init__.py
odoo_addons/fetchmail_notify_error_to_sender/__openerp__.py
odoo_addons/fetchmail_notify_error_to_sender/data/email_template_data.xml
odoo_addons/fetchmail_notify_error_to_sender/i18n/de.po
odoo_addons/fetchmail_notify_error_to_sender/i18n/es.po
odoo_addons/fetchmail_notify_error_to_sender/i18n/fr.po
odoo_addons/fetchmail_notify_error_to_sender/i18n/it.po
odoo_addons/fetchmail_notify_error_to_sender/i18n/pt_BR.po
odoo_addons/fetchmail_notify_error_to_sender/i18n/pt_PT.po
odoo_addons/fetchmail_notify_error_to_sender/i18n/sl.po
odoo_addons/fetchmail_notify_error_to_sender/i18n/tr.po
odoo_addons/fetchmail_notify_error_to_sender/models/__init__.py
odoo_addons/fetchmail_notify_error_to_sender/models/fetchmail.py
odoo_addons/fetchmail_notify_error_to_sender/models/mail_thread.py
odoo_addons/fetchmail_notify_error_to_sender/static/description/icon.png
odoo_addons/fetchmail_notify_error_to_sender/views/fetchmail_view.xml
