Metadata-Version: 2.0
Name: odoo9-addon-fetchmail-notify-error-to-sender
Version: 9.0.1.0.0
Summary: If fetching mails gives error, send an email to sender
Home-page: https://github.com/OCA/server-tools
Author: Agile Business Group,Eficent,Odoo Community Association (OCA)
Author-email: support@odoo-community.org
License: AGPL-3
Platform: UNKNOWN
Classifier: Programming Language :: Python :: 2.7
Classifier: Framework :: Odoo
Classifier: License :: OSI Approved :: GNU Affero General Public License v3
Requires-Dist: odoo (<9.1a,>=9.0a)
